[
    {
        "repo_name": "spring-boot",
        "fix_commit_hash": "a5ad2b33ab9cf443efb52c9b36562c2100616b53",
        "path_id": 2662,
        "bic": [
            "ff99bb0730c23ce8c46785dfd59cc631f41dcf17"
        ],
        "method_type": "rszz"
    },
    {
        "repo_name": "spring-boot",
        "fix_commit_hash": "08eaa6629445825fb94c59d6f8fa8b318ee50534",
        "path_id": 2663,
        "bic": [],
        "method_type": "none"
    },
    {
        "repo_name": "spring-boot",
        "fix_commit_hash": "e06198e9cbf49312a7c1b3949a7508354705983a",
        "path_id": 2664,
        "bic": [
            "2c4f88e221afa376661c474285e86f53c0dd4f0b"
        ],
        "method_type": "rszz"
    },
    {
        "repo_name": "spring-boot",
        "fix_commit_hash": "aa38d33404829b426699e4723eee62bf97d6ca2f",
        "path_id": 2667,
        "bic": [
            "01137b6fd6ab8bf4946c1feb67cb3fed640aa6e1"
        ],
        "method_type": "rszz"
    },
    {
        "repo_name": "spring-boot",
        "fix_commit_hash": "c2e16768495d2e6223947e4112d5e8cb5a6f4d88",
        "path_id": 2669,
        "bic": [],
        "method_type": "none"
    },
    {
        "repo_name": "spring-boot",
        "fix_commit_hash": "cbd3c39640a201fb816b035537432ec4eaacbda1",
        "path_id": 2672,
        "bic": [
            "b72002142df3fbc46ae85200659088c668656734"
        ],
        "method_type": "rszz"
    },
    {
        "repo_name": "spring-boot",
        "fix_commit_hash": "b641e63466c1bca0e705b2db539adb7dec107004",
        "path_id": 2673,
        "bic": [
            "ab7b48de84f2f15b9f658f5f5df790efbd9cf4aa"
        ],
        "method_type": "rszz"
    },
    {
        "repo_name": "spring-boot",
        "fix_commit_hash": "316b07d3b9bcbff9e5d7f531688f80dbd52318c0",
        "path_id": 2694,
        "bic": [
            "793481843cd93368359df2d3568bfed0410d068e"
        ],
        "method_type": "rszz"
    },
    {
        "repo_name": "spring-boot",
        "fix_commit_hash": "99b830ebe7bee9e8ee1f2bdff981fa24845c3ac0",
        "path_id": 2696,
        "bic": [
            "65acaf885ba8015705e3e478ec11ec293ad5134c"
        ],
        "method_type": "rszz"
    },
    {
        "repo_name": "spring-boot",
        "fix_commit_hash": "65684957eabc66203cc67067c6b88060eda7c7d4",
        "path_id": 2697,
        "bic": [
            "f38a36ff70ea94c3b9f87d37044b3ea6e73d78e5"
        ],
        "method_type": "rszz"
    },
    {
        "repo_name": "spring-boot",
        "fix_commit_hash": "0bd89017b6ea203c44f0f3e31366d33529e98654",
        "path_id": 2698,
        "bic": [],
        "method_type": "none"
    },
    {
        "repo_name": "spring-boot",
        "fix_commit_hash": "000cb943238947fec086ac7f64054182b7a1c9b9",
        "path_id": 5856,
        "bic": [
            "43acc37587977b18a3eb27c6aff716e904e320e6"
        ],
        "method_type": "rszz"
    },
    {
        "repo_name": "spring-boot",
        "fix_commit_hash": "19c69ff743e43730bbca881648e943177162a1ef",
        "path_id": 18139,
        "bic": [
            "5eaafdee9a40fe555139ea440f7fdf3b38438a18"
        ],
        "method_type": "rszz"
    },
    {
        "repo_name": "spring-boot",
        "fix_commit_hash": "931409cdd407bb59a24bd81c9b8caa408874d63e",
        "path_id": 18141,
        "bic": [
            "5f1bbf8c72da1702081da57226304ccb9008a642"
        ],
        "method_type": "rszz"
    },
    {
        "repo_name": "spring-boot",
        "fix_commit_hash": "e39d1d14ea844743affda7e4b1d08400ebf729da",
        "path_id": 18142,
        "bic": [],
        "method_type": "none"
    },
    {
        "repo_name": "spring-boot",
        "fix_commit_hash": "4b694560ebaf2e1724e53b7d684cabc236acdffc",
        "path_id": 18143,
        "bic": [
            "a8592f36d425fa6b9faff59a45e1936e87b2ec9d"
        ],
        "method_type": "rszz"
    },
    {
        "repo_name": "spring-boot",
        "fix_commit_hash": "694ff4f8750362da443630e5eedc3eb255a197aa",
        "path_id": 18144,
        "bic": [
            "392be570039e27106d1c5f08b0f760de62f23a41"
        ],
        "method_type": "rszz"
    },
    {
        "repo_name": "spring-boot",
        "fix_commit_hash": "929d8fcd3c54b002d79ab8520152a1bbb9236983",
        "path_id": 18145,
        "bic": [
            "fc3aa43cc229f1a4681e11c29d98f563a1d49207"
        ],
        "method_type": "rszz"
    },
    {
        "repo_name": "spring-boot",
        "fix_commit_hash": "1342e4970a85a24eb07d955741f884392b79bb7e",
        "path_id": 18146,
        "bic": [
            "cb7ae2e60aa2b9aefcdb166ac36d85a11d675990"
        ],
        "method_type": "rszz"
    },
    {
        "repo_name": "spring-boot",
        "fix_commit_hash": "7ee55817b3aa05a1796f5e62a63bd1e70ade28ec",
        "path_id": 18147,
        "bic": [
            "3d46b06e8d274a92084bd0d75d9458fc5f93f7b0"
        ],
        "method_type": "rszz"
    },
    {
        "repo_name": "spring-boot",
        "fix_commit_hash": "0607af870db4c950713b83359197dab6585df1e0",
        "path_id": 18148,
        "bic": [
            "4af6e7ff998224a16563cd5dd140c295f7196740"
        ],
        "method_type": "rszz"
    },
    {
        "repo_name": "spring-boot",
        "fix_commit_hash": "be7fe85b55a04f3bee38943b3bf48635675a99b1",
        "path_id": 18149,
        "bic": [
            "b4963d2463188153a9dd2e34af6b48dc5b47be51"
        ],
        "method_type": "rszz"
    },
    {
        "repo_name": "spring-boot",
        "fix_commit_hash": "5473cd3abcb4f5f04302903e02a81111275bfaa2",
        "path_id": 18150,
        "bic": [
            "4d3d56abfe3c9ed15744b7d78082f17bf7abb45d"
        ],
        "method_type": "rszz"
    },
    {
        "repo_name": "spring-boot",
        "fix_commit_hash": "6cdbdf9ad3b09b204afe660bfb18d62f2e574c7b",
        "path_id": 3168,
        "bic": [
            "00f9adafd7bcd23191251ebf6ca50f69ef166077"
        ],
        "method_type": "rszz"
    },
    {
        "repo_name": "spring-boot",
        "fix_commit_hash": "ad3e5c04bb6bbd50d615c20bbdccb70528bcc492",
        "path_id": 3169,
        "bic": [],
        "method_type": "none"
    }
]