[
    {
        "repo_name": "apache/pulsar",
        "fix_commit_hash": "a13d5cecdcc0378fd5731af8d965440d938472cb",
        "bic": [
            "9a567747916fab151268db0057d2f21ee71d4b01"
        ],
        "commit_author": "Sanjeev Kulkarni",
        "committer": "Sijie Guo",
        "commit_date": "2017-12-08T18:39:49-08:00",
        "committer_date": "2018-03-03T16:44:09-08:00",
        "changed_files": 8,
        "deletions": 3,
        "insertions": 570,
        "lines": 573,
        "dmm_unit_size": 0.6135593220338983,
        "dmm_unit_complexity": 0.8067796610169492,
        "dmm_unit_interfacing": 0.8677966101694915
    },
    {
        "repo_name": "apache/pulsar",
        "fix_commit_hash": "5ba05cc3d22b5fbc6758c78838b28df1396f9bf4",
        "bic": [
            "92b79d0e2e7b9e7b686dedeaae9725620eb5ec3f"
        ],
        "commit_author": "Rajan",
        "committer": "Matteo Merli",
        "commit_date": "2017-05-23T11:49:03-07:00",
        "committer_date": "2017-05-23T11:49:03-07:00",
        "changed_files": 8,
        "deletions": 38,
        "insertions": 417,
        "lines": 455,
        "dmm_unit_size": 0.11538461538461539,
        "dmm_unit_complexity": 0.6346153846153846,
        "dmm_unit_interfacing": 0.8894230769230769
    },
    {
        "repo_name": "apache/pulsar",
        "fix_commit_hash": "26963dc73be053ba3958ea31a314986682d5deba",
        "bic": [
            "9f849c324969e160f9891203b2a2e4805fae5a1c"
        ],
        "commit_author": "Rajan",
        "committer": "Matteo Merli",
        "commit_date": "2017-04-21T13:54:27-07:00",
        "committer_date": "2017-04-21T13:54:27-07:00",
        "changed_files": 2,
        "deletions": 1,
        "insertions": 62,
        "lines": 63,
        "dmm_unit_size": 0.0,
        "dmm_unit_complexity": 1.0,
        "dmm_unit_interfacing": 1.0
    },
    {
        "repo_name": "apache/pulsar",
        "fix_commit_hash": "a13d5cecdcc0378fd5731af8d965440d938472cb",
        "bic": [
            "9a567747916fab151268db0057d2f21ee71d4b01"
        ],
        "commit_author": "Sanjeev Kulkarni",
        "committer": "Sijie Guo",
        "commit_date": "2017-12-08T18:39:49-08:00",
        "committer_date": "2018-03-03T16:44:09-08:00",
        "changed_files": 8,
        "deletions": 3,
        "insertions": 570,
        "lines": 573,
        "dmm_unit_size": 0.6135593220338983,
        "dmm_unit_complexity": 0.8067796610169492,
        "dmm_unit_interfacing": 0.8677966101694915
    },
    {
        "repo_name": "apache/pulsar",
        "fix_commit_hash": "9f849c324969e160f9891203b2a2e4805fae5a1c",
        "bic": [],
        "commit_author": "Matteo Merli",
        "committer": "Matteo Merli",
        "commit_date": "2016-09-06T22:10:37-07:00",
        "committer_date": "2016-09-06T22:11:15-07:00",
        "changed_files": 622,
        "deletions": 0,
        "insertions": 129878,
        "lines": 129878,
        "dmm_unit_size": 0.45506045110988536,
        "dmm_unit_complexity": 0.7647848059750444,
        "dmm_unit_interfacing": 0.8949149510278925
    },
    {
        "repo_name": "apache/pulsar",
        "fix_commit_hash": "e90b30882df4f7046b481bf1a281bc0574271ec9",
        "bic": [
            "a548bc2e04890b3d478f4e25f0d1896ff5439ac3"
        ],
        "commit_author": "Sanjeev Kulkarni",
        "committer": "Sijie Guo",
        "commit_date": "2017-12-21T15:44:40-08:00",
        "committer_date": "2018-03-03T16:44:10-08:00",
        "changed_files": 2,
        "deletions": 20,
        "insertions": 31,
        "lines": 51,
        "dmm_unit_size": 0.0,
        "dmm_unit_complexity": 1.0,
        "dmm_unit_interfacing": 1.0
    },
    {
        "repo_name": "apache/pulsar",
        "fix_commit_hash": "26963dc73be053ba3958ea31a314986682d5deba",
        "bic": [
            "9f849c324969e160f9891203b2a2e4805fae5a1c"
        ],
        "commit_author": "Rajan",
        "committer": "Matteo Merli",
        "commit_date": "2017-04-21T13:54:27-07:00",
        "committer_date": "2017-04-21T13:54:27-07:00",
        "changed_files": 2,
        "deletions": 1,
        "insertions": 62,
        "lines": 63,
        "dmm_unit_size": 0.0,
        "dmm_unit_complexity": 1.0,
        "dmm_unit_interfacing": 1.0
    },
    {
        "repo_name": "apache/pulsar",
        "fix_commit_hash": "624afe71084aa4aae74af252f0d59669501b0e03",
        "bic": [
            "1b0607a18a798a6747670fe621f436172491b1fa"
        ],
        "commit_author": "Sanjeev Kulkarni",
        "committer": "Sijie Guo",
        "commit_date": "2018-01-17T21:41:55-08:00",
        "committer_date": "2018-03-03T16:44:12-08:00",
        "changed_files": 13,
        "deletions": 53,
        "insertions": 52,
        "lines": 105,
        "dmm_unit_size": null,
        "dmm_unit_complexity": null,
        "dmm_unit_interfacing": null
    },
    {
        "repo_name": "apache/pulsar",
        "fix_commit_hash": "12f896ee70f5911ee04e5dafde04ede1921ccb0b",
        "bic": [
            "4dbe9d34235853bc64eb3f38816ffe014308492d"
        ],
        "commit_author": "Rajan",
        "committer": "Matteo Merli",
        "commit_date": "2017-01-10T04:31:56-08:00",
        "committer_date": "2017-01-10T04:31:56-08:00",
        "changed_files": 4,
        "deletions": 7,
        "insertions": 91,
        "lines": 98,
        "dmm_unit_size": 0.01694915254237288,
        "dmm_unit_complexity": 0.01694915254237288,
        "dmm_unit_interfacing": 0.9830508474576272
    },
    {
        "repo_name": "apache/pulsar",
        "fix_commit_hash": "17630b9c0386143714a12361d01713f695b4a73c",
        "bic": [
            "d89563ce54c0f65a78a75d485539be85c0429015"
        ],
        "commit_author": "sschepens",
        "committer": "Matteo Merli",
        "commit_date": "2017-03-02T00:01:01-03:00",
        "committer_date": "2017-03-01T19:01:01-08:00",
        "changed_files": 2,
        "deletions": 82,
        "insertions": 116,
        "lines": 198,
        "dmm_unit_size": 0.0,
        "dmm_unit_complexity": 0.6764705882352942,
        "dmm_unit_interfacing": 0.5
    },
    {
        "repo_name": "apache/pulsar",
        "fix_commit_hash": "73d50b6c9881b457ad633c5f8dda34d2ba6af214",
        "bic": [
            "26963dc73be053ba3958ea31a314986682d5deba"
        ],
        "commit_author": "Rajan Dhabalia",
        "committer": "Matteo Merli",
        "commit_date": "2017-07-25T11:19:12-07:00",
        "committer_date": "2017-07-25T11:19:12-07:00",
        "changed_files": 2,
        "deletions": 3,
        "insertions": 23,
        "lines": 26,
        "dmm_unit_size": 1.0,
        "dmm_unit_complexity": 1.0,
        "dmm_unit_interfacing": 1.0
    },
    {
        "repo_name": "apache/pulsar",
        "fix_commit_hash": "73d50b6c9881b457ad633c5f8dda34d2ba6af214",
        "bic": [
            "26963dc73be053ba3958ea31a314986682d5deba"
        ],
        "commit_author": "Rajan Dhabalia",
        "committer": "Matteo Merli",
        "commit_date": "2017-07-25T11:19:12-07:00",
        "committer_date": "2017-07-25T11:19:12-07:00",
        "changed_files": 2,
        "deletions": 3,
        "insertions": 23,
        "lines": 26,
        "dmm_unit_size": 1.0,
        "dmm_unit_complexity": 1.0,
        "dmm_unit_interfacing": 1.0
    },
    {
        "repo_name": "apache/pulsar",
        "fix_commit_hash": "26963dc73be053ba3958ea31a314986682d5deba",
        "bic": [
            "9f849c324969e160f9891203b2a2e4805fae5a1c"
        ],
        "commit_author": "Rajan",
        "committer": "Matteo Merli",
        "commit_date": "2017-04-21T13:54:27-07:00",
        "committer_date": "2017-04-21T13:54:27-07:00",
        "changed_files": 2,
        "deletions": 1,
        "insertions": 62,
        "lines": 63,
        "dmm_unit_size": 0.0,
        "dmm_unit_complexity": 1.0,
        "dmm_unit_interfacing": 1.0
    },
    {
        "repo_name": "apache/pulsar",
        "fix_commit_hash": "ec46e1a4c5b3f37b743397d356ff4c471de4caed",
        "bic": [
            "493e54ae1fef1fd41f4f7a2f0797f06e5034a8cc"
        ],
        "commit_author": "Sanjeev Kulkarni",
        "committer": "Sijie Guo",
        "commit_date": "2018-01-10T12:07:14-08:00",
        "committer_date": "2018-03-03T16:44:11-08:00",
        "changed_files": 7,
        "deletions": 34,
        "insertions": 12,
        "lines": 46,
        "dmm_unit_size": 0.5384615384615384,
        "dmm_unit_complexity": 0.07692307692307693,
        "dmm_unit_interfacing": 0.23076923076923078
    },
    {
        "repo_name": "apache/pulsar",
        "fix_commit_hash": "aa40ebbe02f9b4f60b7f3910c293c50c18f35687",
        "bic": [
            "73d50b6c9881b457ad633c5f8dda34d2ba6af214"
        ],
        "commit_author": "Rajan Dhabalia",
        "committer": "GitHub",
        "commit_date": "2017-08-31T10:27:25-07:00",
        "committer_date": "2017-08-31T10:27:25-07:00",
        "changed_files": 4,
        "deletions": 33,
        "insertions": 152,
        "lines": 185,
        "dmm_unit_size": 0.34146341463414637,
        "dmm_unit_complexity": 0.8658536585365854,
        "dmm_unit_interfacing": 1.0
    },
    {
        "repo_name": "apache/pulsar",
        "fix_commit_hash": "bb357161d4f091aa17dc4f32f9a16f72324a9d0b",
        "bic": [
            "9f849c324969e160f9891203b2a2e4805fae5a1c"
        ],
        "commit_author": "Rajan",
        "committer": "Matteo Merli",
        "commit_date": "2016-10-07T10:17:25-07:00",
        "committer_date": "2016-10-07T10:17:25-07:00",
        "changed_files": 2,
        "deletions": 1,
        "insertions": 89,
        "lines": 90,
        "dmm_unit_size": 0.14754098360655737,
        "dmm_unit_complexity": 0.14754098360655737,
        "dmm_unit_interfacing": 1.0
    },
    {
        "repo_name": "apache/pulsar",
        "fix_commit_hash": "aca6ac5a7b6bef1f794e9b82bd0b2d0078983408",
        "bic": [
            "a13d5cecdcc0378fd5731af8d965440d938472cb"
        ],
        "commit_author": "Sijie Guo",
        "committer": "Sijie Guo",
        "commit_date": "2017-12-11T14:04:38-08:00",
        "committer_date": "2018-03-03T16:44:09-08:00",
        "changed_files": 11,
        "deletions": 57,
        "insertions": 460,
        "lines": 517,
        "dmm_unit_size": 0.2112676056338028,
        "dmm_unit_complexity": 1.0,
        "dmm_unit_interfacing": 1.0
    },
    {
        "repo_name": "apache/pulsar",
        "fix_commit_hash": "21aec146b1b3c3f9d34d6c0aa48edbddf7d80b05",
        "bic": [
            "0863c22798bb81af753a2ae342dd1c7c85d9c858"
        ],
        "commit_author": "Sijie Guo",
        "committer": "Sijie Guo",
        "commit_date": "2018-01-25T17:00:14-08:00",
        "committer_date": "2018-03-03T16:44:12-08:00",
        "changed_files": 16,
        "deletions": 17,
        "insertions": 342,
        "lines": 359,
        "dmm_unit_size": 0.09009009009009009,
        "dmm_unit_complexity": 0.10810810810810811,
        "dmm_unit_interfacing": 0.8108108108108109
    },
    {
        "repo_name": "apache/pulsar",
        "fix_commit_hash": "3008a4bd87b246eebbe1c7d187e19ffef86ccdbc",
        "bic": [],
        "commit_author": "penghui",
        "committer": "Sijie Guo",
        "commit_date": "2018-11-21T04:10:01+08:00",
        "committer_date": "2018-11-20T12:10:01-08:00",
        "changed_files": 13,
        "deletions": 1,
        "insertions": 608,
        "lines": 609,
        "dmm_unit_size": 0.6158730158730159,
        "dmm_unit_complexity": 0.8888888888888888,
        "dmm_unit_interfacing": 0.9301587301587302
    },
    {
        "repo_name": "apache/pulsar",
        "fix_commit_hash": "9f849c324969e160f9891203b2a2e4805fae5a1c",
        "bic": [],
        "commit_author": "Matteo Merli",
        "committer": "Matteo Merli",
        "commit_date": "2016-09-06T22:10:37-07:00",
        "committer_date": "2016-09-06T22:11:15-07:00",
        "changed_files": 622,
        "deletions": 0,
        "insertions": 129878,
        "lines": 129878,
        "dmm_unit_size": 0.45506045110988536,
        "dmm_unit_complexity": 0.7647848059750444,
        "dmm_unit_interfacing": 0.8949149510278925
    },
    {
        "repo_name": "apache/pulsar",
        "fix_commit_hash": "493e54ae1fef1fd41f4f7a2f0797f06e5034a8cc",
        "bic": [
            "e90b30882df4f7046b481bf1a281bc0574271ec9"
        ],
        "commit_author": "Sanjeev Kulkarni",
        "committer": "Sijie Guo",
        "commit_date": "2018-01-08T23:13:39-08:00",
        "committer_date": "2018-03-03T16:44:11-08:00",
        "changed_files": 16,
        "deletions": 27,
        "insertions": 31,
        "lines": 58,
        "dmm_unit_size": 1.0,
        "dmm_unit_complexity": 1.0,
        "dmm_unit_interfacing": 1.0
    },
    {
        "repo_name": "apache/pulsar",
        "fix_commit_hash": "82f9adb4218374590b662a9cc81713122eeda6e3",
        "bic": [
            "3e4e12760572d931ba317fbf4f0ec0133e17851e"
        ],
        "commit_author": "Rajan",
        "committer": "GitHub",
        "commit_date": "2017-02-24T15:57:40-08:00",
        "committer_date": "2017-02-24T15:57:40-08:00",
        "changed_files": 11,
        "deletions": 4,
        "insertions": 218,
        "lines": 222,
        "dmm_unit_size": 0.0,
        "dmm_unit_complexity": 0.09090909090909091,
        "dmm_unit_interfacing": 0.946969696969697
    }
]