[
    {
        "fix_commit_hash": "d99a37bc07684cba9b7fc6914915b0e0caddaeb5",
        "repo_name": "jabref",
        "best_scenario_issue_date": "2016-08-29T15:22:55+02:00",
        "matched": [
            "fc0129e0f89ee9d3143f6ea7f21a895f4397696e"
        ],
        "commit_author": "Oscar Gustafsson",
        "commiter": "Stefan Kolb",
        "commit_date": "2016-08-29T15:21:55+02:00",
        "committer_data": "2016-08-29T15:21:55+02:00",
        "modified_files": 19,
        "changed_files": 19,
        "deletions": 164,
        "insertions": 3,
        "lines": 167,
        "dmm_unit_size": 0.819672131147541,
        "dmm_unit_complexity": 0.819672131147541,
        "dmm_unit_interfacing": 0.819672131147541,
        "test_changes": "No"
    },
    {
        "fix_commit_hash": "3e7e58a0778448a5e1129c311d599955bde877e0",
        "repo_name": "jabref",
        "best_scenario_issue_date": "2024-01-15T21:56:18+01:00",
        "matched": [
            "b521028419d4f9bb271bf259f9100388960e4398"
        ],
        "commit_author": "Carl Christian Snethlage",
        "commiter": "GitHub",
        "commit_date": "2024-01-15T21:55:18+01:00",
        "committer_data": "2024-01-15T20:55:18+00:00",
        "modified_files": 6,
        "changed_files": 6,
        "deletions": 248,
        "insertions": 214,
        "lines": 462,
        "dmm_unit_size": 0.0,
        "dmm_unit_complexity": 1.0,
        "dmm_unit_interfacing": 0.0,
        "test_changes": "No"
    },
    {
        "fix_commit_hash": "e1da33d4bcf5c91f155a9459aa42d05f81aedcd5",
        "repo_name": "jabref",
        "best_scenario_issue_date": "2024-05-27T21:49:12+02:00",
        "matched": [
            "64a827d8a4f360acdf4a92fb6caa1c481096c63d"
        ],
        "commit_author": "Oliver Kopp",
        "commiter": "GitHub",
        "commit_date": "2024-05-27T21:48:12+02:00",
        "committer_data": "2024-05-27T19:48:12+00:00",
        "modified_files": 3,
        "changed_files": 3,
        "deletions": 7,
        "insertions": 10,
        "lines": 17,
        "dmm_unit_size": 0.0,
        "dmm_unit_complexity": 0.0,
        "dmm_unit_interfacing": 1.0,
        "test_changes": "No"
    },
    {
        "fix_commit_hash": "c75b5d2bc3228c32f2f5b4f4f70444b9d187cb57",
        "repo_name": "jabref",
        "best_scenario_issue_date": "2018-02-16T17:18:40+01:00",
        "matched": [
            "8165e0e4135f39765d2134c19679509da01c2237"
        ],
        "commit_author": "Tobias Diez",
        "commiter": "Tobias Diez",
        "commit_date": "2018-02-16T17:17:40+01:00",
        "committer_data": "2018-02-16T17:17:40+01:00",
        "modified_files": 9,
        "changed_files": 9,
        "deletions": 192,
        "insertions": 118,
        "lines": 310,
        "dmm_unit_size": 0.0,
        "dmm_unit_complexity": 0.75,
        "dmm_unit_interfacing": 1.0,
        "test_changes": "No"
    },
    {
        "fix_commit_hash": "a93ed9b757c287629ff809b8d49ee0863e4073d4",
        "repo_name": "jabref",
        "best_scenario_issue_date": "2018-03-18T16:20:51+01:00",
        "matched": [
            "2cdf085ca094e640073774764551296ff03d1f8f"
        ],
        "commit_author": "Siedlerchr",
        "commiter": "Siedlerchr",
        "commit_date": "2018-03-18T16:19:51+01:00",
        "committer_data": "2018-03-18T16:19:51+01:00",
        "modified_files": 11,
        "changed_files": 11,
        "deletions": 123,
        "insertions": 110,
        "lines": 233,
        "dmm_unit_size": 0.0,
        "dmm_unit_complexity": 0.0,
        "dmm_unit_interfacing": 0.0,
        "test_changes": "No"
    },
    {
        "fix_commit_hash": "f5471a01d45e3afce97db041e0b1ee52dcfaa43c",
        "repo_name": "jabref",
        "best_scenario_issue_date": "2016-04-07T17:09:50+02:00",
        "matched": [
            "644813757d3fa9cf77c3934ae0e695dca4433585"
        ],
        "commit_author": "Christoph",
        "commiter": "Stefan Kolb",
        "commit_date": "2016-04-07T17:08:50+02:00",
        "committer_data": "2016-04-07T17:08:50+02:00",
        "modified_files": 5,
        "changed_files": 5,
        "deletions": 50,
        "insertions": 60,
        "lines": 110,
        "dmm_unit_size": 1.0,
        "dmm_unit_complexity": 1.0,
        "dmm_unit_interfacing": 1.0,
        "test_changes": "No"
    },
    {
        "fix_commit_hash": "59d9e35f786de875b068927acc425a7165ffe49f",
        "repo_name": "jabref",
        "best_scenario_issue_date": "2016-12-12T12:00:23+01:00",
        "matched": [
            "f5ed5ac4d3a2044966ab4df90430abf48125a2d0"
        ],
        "commit_author": "Stefan Kolb",
        "commiter": "Christoph",
        "commit_date": "2016-12-12T11:59:23+01:00",
        "committer_data": "2016-12-12T11:59:23+01:00",
        "modified_files": 6,
        "changed_files": 6,
        "deletions": 26,
        "insertions": 43,
        "lines": 69,
        "dmm_unit_size": 0.42857142857142855,
        "dmm_unit_complexity": 0.42857142857142855,
        "dmm_unit_interfacing": 0.8571428571428571,
        "test_changes": "No"
    },
    {
        "fix_commit_hash": "c3a898fc0978156a13a547d6f08c43510b925ea7",
        "repo_name": "jabref",
        "best_scenario_issue_date": "2017-07-18T19:30:27+02:00",
        "matched": [
            "dbd45bbb28ba38f4f0ee44af7a5be16f0cfc1ee2"
        ],
        "commit_author": "Linus Dietz",
        "commiter": "Linus Dietz",
        "commit_date": "2017-07-18T19:29:27+02:00",
        "committer_data": "2017-07-18T19:36:10+02:00",
        "modified_files": 2,
        "changed_files": 2,
        "deletions": 4,
        "insertions": 4,
        "lines": 8,
        "dmm_unit_size": null,
        "dmm_unit_complexity": null,
        "dmm_unit_interfacing": null,
        "test_changes": "No"
    },
    {
        "fix_commit_hash": "f6651cfc5f88544d2cc9a17bb83de3634ecfebe7",
        "repo_name": "jabref",
        "best_scenario_issue_date": "2017-10-25T11:41:33+02:00",
        "matched": [
            "04afe50e185df0c69e25f112376556321a887bab"
        ],
        "commit_author": "Patrick Scheibe",
        "commiter": "J\u00f6rg Lenhard",
        "commit_date": "2017-10-25T11:40:33+02:00",
        "committer_data": "2017-10-25T11:40:33+02:00",
        "modified_files": 5,
        "changed_files": 5,
        "deletions": 38,
        "insertions": 69,
        "lines": 107,
        "dmm_unit_size": 1.0,
        "dmm_unit_complexity": 1.0,
        "dmm_unit_interfacing": 1.0,
        "test_changes": "No"
    },
    {
        "fix_commit_hash": "b46bf280d6cf82d37ad043bfa1110d33e00cb887",
        "repo_name": "jabref",
        "best_scenario_issue_date": "2016-03-20T22:17:46+01:00",
        "matched": [
            "db0252eedebc2e2eb17e8e3c33046c7693361a2d"
        ],
        "commit_author": "Christian Bartsch",
        "commiter": "Christian Bartsch",
        "commit_date": "2016-03-20T22:16:46+01:00",
        "committer_data": "2016-03-21T13:05:01+01:00",
        "modified_files": 4,
        "changed_files": 4,
        "deletions": 64,
        "insertions": 131,
        "lines": 195,
        "dmm_unit_size": 1.0,
        "dmm_unit_complexity": 1.0,
        "dmm_unit_interfacing": 1.0,
        "test_changes": "Yes"
    },
    {
        "fix_commit_hash": "accd387297c8044a13b1fed924ab004a5acf0627",
        "repo_name": "jabref",
        "best_scenario_issue_date": "2020-04-17T16:19:04+02:00",
        "matched": [
            "347b5e8cd3824dd5bd2747cb0492361540614959"
        ],
        "commit_author": "Tobias Diez",
        "commiter": "GitHub",
        "commit_date": "2020-04-17T16:18:04+02:00",
        "committer_data": "2020-04-17T16:18:04+02:00",
        "modified_files": 6,
        "changed_files": 6,
        "deletions": 205,
        "insertions": 95,
        "lines": 300,
        "dmm_unit_size": 0.027777777777777776,
        "dmm_unit_complexity": 0.0,
        "dmm_unit_interfacing": 0.0,
        "test_changes": "Yes"
    },
    {
        "fix_commit_hash": "401050bb1020fd07a39c8d5991624902c1a70969",
        "repo_name": "jabref",
        "best_scenario_issue_date": "2017-11-12T23:03:20+08:00",
        "matched": [
            "b61cc98e5dd4e14c43cd4fd1afc1735b8cc98709"
        ],
        "commit_author": "Tobias Diez",
        "commiter": "Tobias Diez",
        "commit_date": "2017-11-12T23:02:20+08:00",
        "committer_data": "2017-11-12T23:02:20+08:00",
        "modified_files": 7,
        "changed_files": 7,
        "deletions": 345,
        "insertions": 208,
        "lines": 553,
        "dmm_unit_size": 0.7912087912087912,
        "dmm_unit_complexity": 0.17582417582417584,
        "dmm_unit_interfacing": 0.0,
        "test_changes": "No"
    },
    {
        "fix_commit_hash": "676401627cd77acd23c5a9101b86e6f14fc65ee2",
        "repo_name": "jabref",
        "best_scenario_issue_date": "2005-04-03T08:49:14+00:00",
        "matched": [
            "405770dd524e13a7527005c04707035c9536250b"
        ],
        "commit_author": "jzieren",
        "commiter": "jzieren",
        "commit_date": "2005-04-03T08:48:14+00:00",
        "committer_data": "2005-04-03T08:48:14+00:00",
        "modified_files": 1,
        "changed_files": 1,
        "deletions": 5,
        "insertions": 2,
        "lines": 7,
        "dmm_unit_size": null,
        "dmm_unit_complexity": null,
        "dmm_unit_interfacing": null,
        "test_changes": "No"
    },
    {
        "fix_commit_hash": "9422c4518caf1bfd7df82b8109972f334f22e2a8",
        "repo_name": "jabref",
        "best_scenario_issue_date": "2023-08-29T01:44:31+02:00",
        "matched": [
            "e13dd1446ddff15731737e808a3dd5c6dd3a490c"
        ],
        "commit_author": "Oliver Kopp",
        "commiter": "Oliver Kopp",
        "commit_date": "2023-08-29T01:43:31+02:00",
        "committer_data": "2023-08-29T01:43:31+02:00",
        "modified_files": 1,
        "changed_files": 1,
        "deletions": 1,
        "insertions": 1,
        "lines": 2,
        "dmm_unit_size": null,
        "dmm_unit_complexity": null,
        "dmm_unit_interfacing": null,
        "test_changes": "No"
    },
    {
        "fix_commit_hash": "5dca3b67034d289fcc98b7ddda5acd0892592cfc",
        "repo_name": "jabref",
        "best_scenario_issue_date": "2018-09-23T21:02:14+02:00",
        "matched": [
            "2d5908a7ae171e00deb6e930cc6270d9f5a8c3b0"
        ],
        "commit_author": "Tobias Diez",
        "commiter": "GitHub",
        "commit_date": "2018-09-23T21:01:14+02:00",
        "committer_data": "2018-09-23T21:01:14+02:00",
        "modified_files": 7,
        "changed_files": 7,
        "deletions": 172,
        "insertions": 82,
        "lines": 254,
        "dmm_unit_size": 0.0,
        "dmm_unit_complexity": 0.0,
        "dmm_unit_interfacing": 0.88,
        "test_changes": "No"
    },
    {
        "fix_commit_hash": "8780a5632c5cddc9efb319b3fe99731097b07d5d",
        "repo_name": "jabref",
        "best_scenario_issue_date": "2019-11-24T13:02:12-06:00",
        "matched": [
            "6a37f2f19401b42ef29a51e2ae3f0a9252f8b9a3"
        ],
        "commit_author": "Sam Robertson",
        "commiter": "Tobias Diez",
        "commit_date": "2019-11-24T13:01:12-06:00",
        "committer_data": "2019-11-24T20:01:12+01:00",
        "modified_files": 7,
        "changed_files": 7,
        "deletions": 8,
        "insertions": 29,
        "lines": 37,
        "dmm_unit_size": 0.6,
        "dmm_unit_complexity": 1.0,
        "dmm_unit_interfacing": 1.0,
        "test_changes": "No"
    },
    {
        "fix_commit_hash": "769090b229a72b50197b8d77485da7d029a44cd3",
        "repo_name": "jabref",
        "best_scenario_issue_date": "2015-05-11T21:39:47+02:00",
        "matched": [
            "3125b1fdc5482192ff94a1e763489bcf92ac559d"
        ],
        "commit_author": "Tobias",
        "commiter": "Tobias",
        "commit_date": "2015-05-11T21:38:47+02:00",
        "committer_data": "2015-05-11T21:38:47+02:00",
        "modified_files": 4,
        "changed_files": 4,
        "deletions": 1,
        "insertions": 15,
        "lines": 16,
        "dmm_unit_size": 0.0,
        "dmm_unit_complexity": 0.0,
        "dmm_unit_interfacing": 1.0,
        "test_changes": "No"
    },
    {
        "fix_commit_hash": "1c3802edd9c8d84905f5374810013f1305dc44f3",
        "repo_name": "jabref",
        "best_scenario_issue_date": "2019-10-07T16:20:27+02:00",
        "matched": [
            "124fadb698a373265494c5d6f3308163c46ab1f9"
        ],
        "commit_author": "Galileo Sartor",
        "commiter": "Tobias Diez",
        "commit_date": "2019-10-07T16:19:27+02:00",
        "committer_data": "2019-10-07T16:19:27+02:00",
        "modified_files": 3,
        "changed_files": 3,
        "deletions": 344,
        "insertions": 26,
        "lines": 370,
        "dmm_unit_size": 0.6445783132530121,
        "dmm_unit_complexity": 0.25301204819277107,
        "dmm_unit_interfacing": 0.0963855421686747,
        "test_changes": "No"
    },
    {
        "fix_commit_hash": "bd7e23f13e109342bad103ccabd5a8305b033494",
        "repo_name": "jabref",
        "best_scenario_issue_date": "2016-06-01T10:28:02+02:00",
        "matched": [
            "9021933fbc989cb5ca04b7c9aae87ea36ae4158d"
        ],
        "commit_author": "Oscar Gustafsson",
        "commiter": "Stefan Kolb",
        "commit_date": "2016-06-01T10:27:02+02:00",
        "committer_data": "2016-06-01T10:27:02+02:00",
        "modified_files": 1,
        "changed_files": 1,
        "deletions": 29,
        "insertions": 29,
        "lines": 58,
        "dmm_unit_size": null,
        "dmm_unit_complexity": null,
        "dmm_unit_interfacing": null,
        "test_changes": "No"
    },
    {
        "fix_commit_hash": "c59f8c83e75e1ca9a84d934e0cee7611d2011f4e",
        "repo_name": "jabref",
        "best_scenario_issue_date": "2019-11-27T20:47:22+01:00",
        "matched": [
            "d1484f89956f1eb694a3b9eb6d52bd9b66ebafa1"
        ],
        "commit_author": "Tobias Diez",
        "commiter": "GitHub",
        "commit_date": "2019-11-27T20:46:22+01:00",
        "committer_data": "2019-11-27T20:46:22+01:00",
        "modified_files": 4,
        "changed_files": 4,
        "deletions": 34,
        "insertions": 78,
        "lines": 112,
        "dmm_unit_size": 0.0,
        "dmm_unit_complexity": 0.0,
        "dmm_unit_interfacing": 0.8378378378378378,
        "test_changes": "No"
    }
]