[
    {
        "repo_name": "junit-framework",
        "fix_commit_hash": "ae9b05434fa1d7dfa5b9ff2096189b30ef6e1d6c",
        "path_id": 904
    },
    {
        "repo_name": "junit-framework",
        "fix_commit_hash": "62e6078ac9c9a8109a28fd8ab1116976bdb28dd4",
        "path_id": 381
    },
    {
        "repo_name": "junit-framework",
        "fix_commit_hash": "1d8c684482af35043ad2c95cd0d10d9d43dde56f",
        "path_id": 383
    },
    {
        "repo_name": "junit-framework",
        "fix_commit_hash": "d6b17576a2b7e2d1ba28dbef2430c042ad1b887a",
        "path_id": 864
    },
    {
        "repo_name": "junit-framework",
        "fix_commit_hash": "b6814577e06fc09024ba4739db24a72725cc4d41",
        "path_id": 446
    },
    {
        "repo_name": "junit-framework",
        "fix_commit_hash": "55316795906dcac64c8ec3ea5eeffbdf758c3383",
        "path_id": 433
    },
    {
        "repo_name": "junit-framework",
        "fix_commit_hash": "b55b5fad31b185f9e07d28cda5649be97cb0a219",
        "path_id": 434
    },
    {
        "repo_name": "junit-framework",
        "fix_commit_hash": "7e1e67ec06ab89856e46246a9af3054451f046e8",
        "path_id": 436
    },
    {
        "repo_name": "junit-framework",
        "fix_commit_hash": "9f7d082872c4b4109729a3a480f1dedad3083bad",
        "path_id": 115
    },
    {
        "repo_name": "junit-framework",
        "fix_commit_hash": "cfa12293c6ff5b0205730e45326f2344bca55b25",
        "path_id": 116
    }
]