[
    {
        "repo_name": "junit-framework",
        "fix_commit_hash": "309a696f4f7a2cda191521b43b0f2482832a6123",
        "path_id": 845
    },
    {
        "repo_name": "junit-framework",
        "fix_commit_hash": "6183a6356cd58ecabdeee8c7a6c840d3540bf73a",
        "path_id": 847
    },
    {
        "repo_name": "junit-framework",
        "fix_commit_hash": "da9cf72c906337dd3a6ec0d88407a6869ab76c91",
        "path_id": 848
    },
    {
        "repo_name": "junit-framework",
        "fix_commit_hash": "24d01603994b86782e183d4c4fb6d3adfb03a01a",
        "path_id": 849
    },
    {
        "repo_name": "junit-framework",
        "fix_commit_hash": "48276fd094821f79afb3cd384b8c70946d73350b",
        "path_id": 850
    },
    {
        "repo_name": "junit-framework",
        "fix_commit_hash": "76798154560189d391f6f49e2db65ddbad70fe17",
        "path_id": 901
    },
    {
        "repo_name": "junit-framework",
        "fix_commit_hash": "5a3d8828cccd1a87244ea30e7c980f46570265e8",
        "path_id": 902
    },
    {
        "repo_name": "junit-framework",
        "fix_commit_hash": "d52ddac62126167ff1cae6ccac6640d7664e249c",
        "path_id": 904
    },
    {
        "repo_name": "junit-framework",
        "fix_commit_hash": "6a4cb0643b7d49dccbebaba8a7935331e4023022",
        "path_id": 905
    },
    {
        "repo_name": "junit-framework",
        "fix_commit_hash": "73a039cc68eec20b9870b77acd7d0e16bbcb6fb8",
        "path_id": 906
    }
]