[
    {
        "repo_name": "keycloak",
        "fix_commit_hash": "00e4c3567a485c7f543da849f147d323a4a33712",
        "path_id": 2600
    },
    {
        "repo_name": "keycloak",
        "fix_commit_hash": "f20cdd6d2ad82fdcb0d3e0eb62510c488de8753b",
        "path_id": 2001
    },
    {
        "repo_name": "keycloak",
        "fix_commit_hash": "fd2cd688b87dd7aa3c6a049f8184f8af62a8881a",
        "path_id": 2002
    },
    {
        "repo_name": "keycloak",
        "fix_commit_hash": "f627e9535fcadf729ebeba48a59f0be7f90277a8",
        "path_id": 2005
    },
    {
        "repo_name": "keycloak",
        "fix_commit_hash": "b54bb251218279b865bb9f8f094bad500dadc72e",
        "path_id": 2006
    },
    {
        "repo_name": "keycloak",
        "fix_commit_hash": "384d7c17f7f4dc25edd309ead4d80546405dbd03",
        "path_id": 5644
    },
    {
        "repo_name": "keycloak",
        "fix_commit_hash": "cec9717dd2a53118caf29649f6896701683f28b9",
        "path_id": 5648
    },
    {
        "repo_name": "keycloak",
        "fix_commit_hash": "0aa14c19e11752898935c36ea7df55a0aa72a5aa",
        "path_id": 5650
    },
    {
        "repo_name": "keycloak",
        "fix_commit_hash": "8d8fae5def832220cf00516e7709c7500fdb9aa8",
        "path_id": 451
    },
    {
        "repo_name": "keycloak",
        "fix_commit_hash": "92cce7a6d4398db23f6c3481d9dc2f3b96530696",
        "path_id": 464
    }
]