[
    {
        "fix_commit_hash": "95dbe6eb6d12743547aba39d40aea4f8d37c390e",
        "repo_name": "jabref",
        "best_scenario_issue_date": "2015-12-01T14:01:36+01:00",
        "matched": [
            "e30383bce46a3d252c9ce8f1f3f9932e99f4fe72"
        ],
        "commit_author": "Joerg Lenhard",
        "commiter": "Joerg Lenhard",
        "commit_date": "2015-12-01T14:00:36+01:00",
        "committer_data": "2015-12-01T14:00:36+01:00",
        "modified_files": 1,
        "changed_files": 1,
        "deletions": 13,
        "insertions": 41,
        "lines": 54,
        "dmm_unit_size": 0.5294117647058824,
        "dmm_unit_complexity": 0.5294117647058824,
        "dmm_unit_interfacing": 1.0,
        "test_changes": "No",
        "files_with_tests": 0
    },
    {
        "fix_commit_hash": "d77c746f2c68306cec8a622a0e8b3e6bea6d727e",
        "repo_name": "jabref",
        "best_scenario_issue_date": "2015-11-26T17:05:43+01:00",
        "matched": [
            "fc356bf3fb80d55074cfab5364703fd9a357221b"
        ],
        "commit_author": "Simon Harrer",
        "commiter": "Simon Harrer",
        "commit_date": "2015-11-26T17:04:43+01:00",
        "committer_data": "2015-11-26T17:04:43+01:00",
        "modified_files": 2,
        "changed_files": 2,
        "deletions": 20,
        "insertions": 10,
        "lines": 30,
        "dmm_unit_size": 1.0,
        "dmm_unit_complexity": 0.0,
        "dmm_unit_interfacing": 0.0,
        "test_changes": "No",
        "files_with_tests": 0
    },
    {
        "fix_commit_hash": "7255494036c8c762c4a15e440e5038ca3dee9490",
        "repo_name": "jabref",
        "best_scenario_issue_date": "2007-02-18T19:33:01+00:00",
        "matched": [
            "abec0eecb14a7a51587eccd3425d11b7d7fecd40"
        ],
        "commit_author": "mortenalver",
        "commiter": "mortenalver",
        "commit_date": "2007-02-18T19:32:01+00:00",
        "committer_data": "2007-02-18T19:32:01+00:00",
        "modified_files": 5,
        "changed_files": 5,
        "deletions": 58,
        "insertions": 143,
        "lines": 201,
        "dmm_unit_size": 0.36,
        "dmm_unit_complexity": 1.0,
        "dmm_unit_interfacing": 1.0,
        "test_changes": "No",
        "files_with_tests": 0
    },
    {
        "fix_commit_hash": "25d2a420928f1d2a54466c1cefbd7d9d25f534e2",
        "repo_name": "jabref",
        "best_scenario_issue_date": "2006-10-19T21:42:13+00:00",
        "matched": [
            "355083f5019de8994520d617fa62d5a11cde97f5"
        ],
        "commit_author": "mortenalver",
        "commiter": "mortenalver",
        "commit_date": "2006-10-19T21:41:13+00:00",
        "committer_data": "2006-10-19T21:41:13+00:00",
        "modified_files": 20,
        "changed_files": 20,
        "deletions": 554,
        "insertions": 599,
        "lines": 1153,
        "dmm_unit_size": 1.0,
        "dmm_unit_complexity": 1.0,
        "dmm_unit_interfacing": 0.0,
        "test_changes": "No",
        "files_with_tests": 0
    },
    {
        "fix_commit_hash": "2b410859e7bf54d167279067541b512da62967d8",
        "repo_name": "jabref",
        "best_scenario_issue_date": "2020-12-21T11:16:45+01:00",
        "matched": [
            "196f9376a900dbd0bd8304bb5328298056ebb6f7"
        ],
        "commit_author": "dependabot[bot]",
        "commiter": "GitHub",
        "commit_date": "2020-12-21T11:15:45+01:00",
        "committer_data": "2020-12-21T11:15:45+01:00",
        "modified_files": 1,
        "changed_files": 1,
        "deletions": 1,
        "insertions": 1,
        "lines": 2,
        "dmm_unit_size": null,
        "dmm_unit_complexity": null,
        "dmm_unit_interfacing": null,
        "test_changes": "No",
        "files_with_tests": 0
    },
    {
        "fix_commit_hash": "a578acc86346df25aee753d04468dba0a40c6cb1",
        "repo_name": "jabref",
        "best_scenario_issue_date": "2018-04-26T11:39:40+02:00",
        "matched": [
            "ab6b416ccb4fc1e3dbe959b0b968cd36dc4520a0"
        ],
        "commit_author": "Stefan Kolb",
        "commiter": "Stefan Kolb",
        "commit_date": "2018-04-26T11:38:40+02:00",
        "committer_data": "2018-04-26T11:38:40+02:00",
        "modified_files": 2,
        "changed_files": 2,
        "deletions": 52,
        "insertions": 4,
        "lines": 56,
        "dmm_unit_size": null,
        "dmm_unit_complexity": null,
        "dmm_unit_interfacing": null,
        "test_changes": "No",
        "files_with_tests": 0
    },
    {
        "fix_commit_hash": "159c48aa27c699bd49798057db2c1aac9752b15e",
        "repo_name": "jabref",
        "best_scenario_issue_date": "2019-02-24T20:18:54+01:00",
        "matched": [
            "5657fed6eefe24c2f018315689779057f460efde"
        ],
        "commit_author": "Siedlerchr",
        "commiter": "Siedlerchr",
        "commit_date": "2019-02-24T20:17:54+01:00",
        "committer_data": "2019-02-24T20:17:54+01:00",
        "modified_files": 9,
        "changed_files": 9,
        "deletions": 88,
        "insertions": 119,
        "lines": 207,
        "dmm_unit_size": 1.0,
        "dmm_unit_complexity": 0.0,
        "dmm_unit_interfacing": 0.0,
        "test_changes": "No",
        "files_with_tests": 0
    },
    {
        "fix_commit_hash": "8f2874a0c54669136ccced7a738a6656b1545d05",
        "repo_name": "jabref",
        "best_scenario_issue_date": "2008-12-03T13:00:38+00:00",
        "matched": [
            "e19e427d82e7d416e9dc113d8977a14fbee2aa8a"
        ],
        "commit_author": "ThomasArildsen",
        "commiter": "ThomasArildsen",
        "commit_date": "2008-12-03T12:59:38+00:00",
        "committer_data": "2008-12-03T12:59:38+00:00",
        "modified_files": 1,
        "changed_files": 1,
        "deletions": 13,
        "insertions": 12,
        "lines": 25,
        "dmm_unit_size": null,
        "dmm_unit_complexity": null,
        "dmm_unit_interfacing": null,
        "test_changes": "No",
        "files_with_tests": 0
    },
    {
        "fix_commit_hash": "f7a5c16cd99a1bf1ccfc208a0c30ad5e55076c1c",
        "repo_name": "jabref",
        "best_scenario_issue_date": "2011-08-12T09:50:32+00:00",
        "matched": [],
        "commit_author": "olly98",
        "commiter": "olly98",
        "commit_date": "2011-08-12T09:49:32+00:00",
        "committer_data": "2011-08-12T09:49:32+00:00",
        "modified_files": 1,
        "changed_files": 1,
        "deletions": 0,
        "insertions": 12,
        "lines": 12,
        "dmm_unit_size": 0.0,
        "dmm_unit_complexity": 0.0,
        "dmm_unit_interfacing": 1.0,
        "test_changes": "No",
        "files_with_tests": 0
    },
    {
        "fix_commit_hash": "cd558a0536a9bfafccde349d95cf7e9fdca07f91",
        "repo_name": "jabref",
        "best_scenario_issue_date": "2016-02-28T12:38:17+01:00",
        "matched": [
            "d94f1530f5594d9e4083fefe4ff36d34b64c540a"
        ],
        "commit_author": "Tobias Diez",
        "commiter": "Tobias Diez",
        "commit_date": "2016-02-28T12:37:17+01:00",
        "committer_data": "2016-03-13T23:13:50+01:00",
        "modified_files": 3,
        "changed_files": 3,
        "deletions": 5,
        "insertions": 3,
        "lines": 8,
        "dmm_unit_size": 1.0,
        "dmm_unit_complexity": 0.0,
        "dmm_unit_interfacing": 0.0,
        "test_changes": "No",
        "files_with_tests": 0
    },
    {
        "fix_commit_hash": "66094f0aac284f26dba5ca4569381f44f442abc5",
        "repo_name": "jabref",
        "best_scenario_issue_date": "2018-07-18T15:14:28+02:00",
        "matched": [
            "dd9b2291160056723c977d33ac31121dda96a459"
        ],
        "commit_author": "Tobias Diez",
        "commiter": "Tobias Diez",
        "commit_date": "2018-07-18T15:13:28+02:00",
        "committer_data": "2018-07-18T15:13:28+02:00",
        "modified_files": 7,
        "changed_files": 7,
        "deletions": 6,
        "insertions": 366,
        "lines": 372,
        "dmm_unit_size": 1.0,
        "dmm_unit_complexity": 1.0,
        "dmm_unit_interfacing": 1.0,
        "test_changes": "No",
        "files_with_tests": 0
    },
    {
        "fix_commit_hash": "bf1314fdfe89019ad16f80b079c014975a7719c4",
        "repo_name": "jabref",
        "best_scenario_issue_date": "2015-11-27T14:32:06+01:00",
        "matched": [
            "db65cf92fe2059908c85c55f3fc66a46a4586bec"
        ],
        "commit_author": "Joerg Lenhard",
        "commiter": "Joerg Lenhard",
        "commit_date": "2015-11-27T14:31:06+01:00",
        "committer_data": "2015-11-27T14:31:06+01:00",
        "modified_files": 1,
        "changed_files": 1,
        "deletions": 1,
        "insertions": 13,
        "lines": 14,
        "dmm_unit_size": 0.0,
        "dmm_unit_complexity": 1.0,
        "dmm_unit_interfacing": 1.0,
        "test_changes": "No",
        "files_with_tests": 0
    },
    {
        "fix_commit_hash": "72e5f52ea9b26d822f6d5ef46a2cb0d4a82510a1",
        "repo_name": "jabref",
        "best_scenario_issue_date": "2006-12-16T16:07:04+00:00",
        "matched": [
            "3e43ad04793c052d5d92f73b697fc422888d57ce"
        ],
        "commit_author": "mortenalver",
        "commiter": "mortenalver",
        "commit_date": "2006-12-16T16:06:04+00:00",
        "committer_data": "2006-12-16T16:06:04+00:00",
        "modified_files": 12,
        "changed_files": 12,
        "deletions": 8,
        "insertions": 35,
        "lines": 43,
        "dmm_unit_size": 0.0,
        "dmm_unit_complexity": 0.5555555555555556,
        "dmm_unit_interfacing": 1.0,
        "test_changes": "No",
        "files_with_tests": 0
    },
    {
        "fix_commit_hash": "cedb4fa905525690f262fa58c1e0e5b5d865fca3",
        "repo_name": "jabref",
        "best_scenario_issue_date": "2016-02-19T11:04:15+01:00",
        "matched": [
            "d94f1530f5594d9e4083fefe4ff36d34b64c540a"
        ],
        "commit_author": "Joerg Lenhard",
        "commiter": "Joerg Lenhard",
        "commit_date": "2016-02-19T11:03:15+01:00",
        "committer_data": "2016-02-19T11:03:15+01:00",
        "modified_files": 18,
        "changed_files": 18,
        "deletions": 3,
        "insertions": 50,
        "lines": 53,
        "dmm_unit_size": null,
        "dmm_unit_complexity": null,
        "dmm_unit_interfacing": null,
        "test_changes": "No",
        "files_with_tests": 0
    },
    {
        "fix_commit_hash": "35790ddde7b3ea1cd8e2e55a24378def810e2910",
        "repo_name": "jabref",
        "best_scenario_issue_date": "2004-10-07T20:52:22+00:00",
        "matched": [
            "ad8acb755ce80fcad1a32f43a5536868d7e4d3f4"
        ],
        "commit_author": "mortenalver",
        "commiter": "mortenalver",
        "commit_date": "2004-10-07T20:51:22+00:00",
        "committer_data": "2004-10-07T20:51:22+00:00",
        "modified_files": 8,
        "changed_files": 8,
        "deletions": 8,
        "insertions": 24,
        "lines": 32,
        "dmm_unit_size": 0.0,
        "dmm_unit_complexity": 1.0,
        "dmm_unit_interfacing": 1.0,
        "test_changes": "No",
        "files_with_tests": 0
    },
    {
        "fix_commit_hash": "93b87e41d0b2f360aa5ea41501dd02f05a2c9672",
        "repo_name": "jabref",
        "best_scenario_issue_date": "2017-03-04T19:20:30+01:00",
        "matched": [
            "0cee93437c52e2f22a1a8c27f1e7a1c006474ea3"
        ],
        "commit_author": "Siedlerchr",
        "commiter": "Siedlerchr",
        "commit_date": "2017-03-04T19:19:30+01:00",
        "committer_data": "2017-03-04T19:19:30+01:00",
        "modified_files": 1,
        "changed_files": 1,
        "deletions": 1,
        "insertions": 1,
        "lines": 2,
        "dmm_unit_size": null,
        "dmm_unit_complexity": null,
        "dmm_unit_interfacing": null,
        "test_changes": "No",
        "files_with_tests": 0
    },
    {
        "fix_commit_hash": "ca73006a6a835057cd27f58971443be8026805ee",
        "repo_name": "jabref",
        "best_scenario_issue_date": "2004-12-20T13:13:28+00:00",
        "matched": [
            "3c2b3dea919b1c1876b3a21e851f3512b0573b2d"
        ],
        "commit_author": "fdar",
        "commiter": "fdar",
        "commit_date": "2004-12-20T13:12:28+00:00",
        "committer_data": "2004-12-20T13:12:28+00:00",
        "modified_files": 1,
        "changed_files": 1,
        "deletions": 1080,
        "insertions": 546,
        "lines": 1626,
        "dmm_unit_size": null,
        "dmm_unit_complexity": null,
        "dmm_unit_interfacing": null,
        "test_changes": "No",
        "files_with_tests": 0
    },
    {
        "fix_commit_hash": "1c7fab1a211496366f6cfbb30a68841dda71f048",
        "repo_name": "jabref",
        "best_scenario_issue_date": "2016-03-18T16:26:22+01:00",
        "matched": [
            "e5640a9d493b56646acef867240b69bef62e716d"
        ],
        "commit_author": "Oscar Gustafsson",
        "commiter": "Oscar Gustafsson",
        "commit_date": "2016-03-18T16:25:22+01:00",
        "committer_data": "2016-03-24T15:49:37+01:00",
        "modified_files": 3,
        "changed_files": 3,
        "deletions": 33,
        "insertions": 38,
        "lines": 71,
        "dmm_unit_size": 1.0,
        "dmm_unit_complexity": 0.0,
        "dmm_unit_interfacing": 0.0,
        "test_changes": "No",
        "files_with_tests": 0
    },
    {
        "fix_commit_hash": "5b98dce0f57781a6e58347bcfddfc8c62047cfa2",
        "repo_name": "jabref",
        "best_scenario_issue_date": "2017-03-31T11:27:38+02:00",
        "matched": [
            "1cc550b6134527620aa3a2c1ab6fe820419db1a6"
        ],
        "commit_author": "Christoph",
        "commiter": "Tobias Diez",
        "commit_date": "2017-03-31T11:26:38+02:00",
        "committer_data": "2017-03-31T11:26:38+02:00",
        "modified_files": 6,
        "changed_files": 6,
        "deletions": 6,
        "insertions": 45,
        "lines": 51,
        "dmm_unit_size": 0.0,
        "dmm_unit_complexity": 0.0,
        "dmm_unit_interfacing": 1.0,
        "test_changes": "No",
        "files_with_tests": 0
    },
    {
        "fix_commit_hash": "5aca23e646951d3b5de5f7f411a871e34b4b5b72",
        "repo_name": "jabref",
        "best_scenario_issue_date": "2015-08-17T20:38:58+02:00",
        "matched": [
            "16aa760463435fd8e945bcd296c075f1811f252b"
        ],
        "commit_author": "stefan-kolb",
        "commiter": "Stefan Kolb",
        "commit_date": "2015-08-17T20:37:58+02:00",
        "committer_data": "2015-10-09T14:46:40+02:00",
        "modified_files": 17,
        "changed_files": 17,
        "deletions": 226,
        "insertions": 154,
        "lines": 380,
        "dmm_unit_size": 0.25,
        "dmm_unit_complexity": 1.0,
        "dmm_unit_interfacing": 1.0,
        "test_changes": "Yes",
        "files_with_tests": 2
    }
]